setup.py
adware/__init__.py
adware/admin.py
adware/apps.py
adware/defaults.py
adware/forms.py
adware/models.py
adware/receivers.py
adware/urls.py
adware/utils.py
adware/views.py
adware/migrations/0001_initial.py
adware/migrations/0002_auto_20160324_2006.py
adware/migrations/0003_auto_20160325_1153.py
adware/migrations/__init__.py
adware/templatetags/__init__.py
adware/templatetags/adsense.py
adware/tests/__init__.py
adware/tests/tests_common.py
adware/tests/tests_models.py
adware/tests/testsettings.py
django_adware.egg-info/PKG-INFO
django_adware.egg-info/SOURCES.txt
django_adware.egg-info/dependency_links.txt
django_adware.egg-info/top_level.txt